pyopenagi/README.md
pyopenagi/__init__.py
pyopenagi/agents/README.md
pyopenagi/agents/__init__.py
pyopenagi/agents/agent_factory.py
pyopenagi/agents/agent_process.py
pyopenagi/agents/base_agent.py
pyopenagi/agents/call_core.py
pyopenagi/agents/interact.py
pyopenagi/agents/react_agent.py
pyopenagi/agents/example/README.md
pyopenagi/agents/example/academic_agent/agent.py
pyopenagi/agents/example/academic_agent/config.json
pyopenagi/agents/example/academic_agent/meta_requirements.txt
pyopenagi/agents/example/cocktail_mixlogist/agent.py
pyopenagi/agents/example/cocktail_mixlogist/config.json
pyopenagi/agents/example/cocktail_mixlogist/meta_requirements.txt
pyopenagi/agents/example/cook_therapist/agent.py
pyopenagi/agents/example/cook_therapist/config.json
pyopenagi/agents/example/cook_therapist/meta_requirements.txt
pyopenagi/agents/example/creation_agent/agent.py
pyopenagi/agents/example/creation_agent/config.json
pyopenagi/agents/example/creation_agent/meta_requirements.txt
pyopenagi/agents/example/fashion_stylist/agent.py
pyopenagi/agents/example/fashion_stylist/config.json
pyopenagi/agents/example/fashion_stylist/meta_requirements.txt
pyopenagi/agents/example/festival_card_designer/agent.py
pyopenagi/agents/example/festival_card_designer/config.json
pyopenagi/agents/example/festival_card_designer/meta_requirements.txt
pyopenagi/agents/example/fitness_trainer/agent.py
pyopenagi/agents/example/fitness_trainer/config.json
pyopenagi/agents/example/fitness_trainer/meta_requirements.txt
pyopenagi/agents/example/game_agent/agent.py
pyopenagi/agents/example/game_agent/config.json
pyopenagi/agents/example/game_agent/meta_requirements.txt
pyopenagi/agents/example/interior_decorator/agent.py
pyopenagi/agents/example/interior_decorator/config.json
pyopenagi/agents/example/interior_decorator/meta_requirements.txt
pyopenagi/agents/example/language_tutor/agent.py
pyopenagi/agents/example/language_tutor/config.json
pyopenagi/agents/example/language_tutor/meta_requirements.txt
pyopenagi-0.0.11.dist-info/METADATA
pyopenagi-0.0.11.dist-info/WHEEL
pyopenagi-0.0.11.dist-info/licenses/LICENSE
pyopenagi-0.0.11.dist-info/RECORD
